apigratis/Service.py
apigratis/__init__.py
apigratis_sdk_python-1.1.7.dist-info/LICENSE
apigratis_sdk_python-1.1.7.dist-info/METADATA
apigratis_sdk_python-1.1.7.dist-info/WHEEL
apigratis_sdk_python-1.1.7.dist-info/entry_points.txt
apigratis_sdk_python-1.1.7.dist-info/top_level.txt
apigratis_sdk_python-1.1.7.dist-info/RECORD
