Metadata-Version: 2.1
Name: apigratis-sdk-python
Version: 1.1.7
Summary: A ideia desse SDK é otimizar o tempo de código dos usuários auxiliando na integração com a plataforma.
Home-page: https://github.com/APIBrasil/apigratis-sdk-python
Author: APIBRASIL
Author-email: APIBRASIL <contato@apibrasil.com.br>
License: MIT License
Project-URL: Homepage, https://github.com/APIBrasil/apigratis-sdk-python
Project-URL: Repository, https://github.com/APIBrasil/apigratis-sdk-python.git
Project-URL: Bug Tracker, https://github.com/APIBrasil/apigratis-sdk-python/issues
Keywords: python,package,build,tutorial
Classifier: Intended Audience :: Developers
Classifier: Programming Language :: Python :: 3
Classifier: License :: OSI Approved :: MIT License
Classifier: Operating System :: OS Independent
Requires-Python: >=3.2
License-File: LICENSE
Requires-Dist: requests
Provides-Extra: dev
Requires-Dist: pytest; extra == "dev"
